README.md
setup.py
tornado_restful/__init__.py
tornado_restful/decorators.py
tornado_restful/exceptions.py
tornado_restful/handlers.py
tornado_restful/i18n.py
tornado_restful/routers.py
tornado_restful/serializers.py
tornado_restful/shortcuts.py
tornado_restful/status.py
tornado_restful/utils.py
tornado_restful.egg-info/PKG-INFO
tornado_restful.egg-info/SOURCES.txt
tornado_restful.egg-info/dependency_links.txt
tornado_restful.egg-info/requires.txt
tornado_restful.egg-info/top_level.txt
tornado_restful/conf/__init__.py
tornado_restful/conf/global_settings.py
tornado_restful/models/__init__.py
tornado_restful/models/base.py
tornado_restful/models/fields.py