Metadata-Version: 2.1
Name: tornado-restful
Version: 1.0.1
Summary: Tornado REST framework
Home-page: https://github.com/245967906/tornado-restful
Author: 245967906
Author-email: 245967906@qq.com
License: UNKNOWN
Platform: UNKNOWN
Classifier: Programming Language :: Python :: 3
Classifier: License :: OSI Approved :: GNU General Public License v3 (GPLv3)
Classifier: Operating System :: OS Independent
Requires-Python: >=3.6
